[
    {
        "RNC_Name": "KAI-RNC-01",
        "3GSiteName": "KAI-3G-001",
        "3GSiteID": "3G001",
        "UtranCellId": "KAI001-1",
        "Sector": "A",
        "Sector_index": 1,
        "cId": 101,
        "primaryCpichPower": 33,
        "primaryScramblingCode": 123,
        "uarfcnDl": 10612,
        "uarfcnUl": 9612,
        "userLabel": "Kairouan North",
        "Lac": 1001,
        "Rac": 21,
        "LAT": 35.6789,
        "LONG": 10.1001,
        "AZIMUTH": 0,
        "P_SiteName": "KAI-SITE-A",
        "administrativeState": "UNLOCKED",
        "operationalState": "ENABLED",
        "Ura": 1,
        "maximumTransmissionPower": 40,
        "NodeId": "NODE-KAI-001",
        "LogicalSite": "Kairouan Zone A",
        "Region": "Kairouan"
    },
    {
        "RNC_Name": "KAI-RNC-01",
        "3GSiteName": "KAI-3G-002",
        "3GSiteID": "3G002",
        "UtranCellId": "KAI002-1",
        "Sector": "B",
        "Sector_index": 2,
        "cId": 102,
        "primaryCpichPower": 33,
        "primaryScramblingCode": 124,
        "uarfcnDl": 10637,
        "uarfcnUl": 9637,
        "userLabel": "Kairouan Center",
        "Lac": 1002,
        "Rac": 22,
        "LAT": 35.6722,
        "LONG": 10.1022,
        "AZIMUTH": 120,
        "P_SiteName": "KAI-SITE-B",
        "administrativeState": "UNLOCKED",
        "operationalState": "ENABLED",
        "Ura": 2,
        "maximumTransmissionPower": 43,
        "NodeId": "NODE-KAI-002",
        "LogicalSite": "Kairouan Center",
        "Region": "Kairouan"
    },
    {
        "RNC_Name": "KAI-RNC-01",
        "3GSiteName": "KAI-3G-003",
        "3GSiteID": "3G003",
        "UtranCellId": "KAI003-1",
        "Sector": "C",
        "Sector_index": 3,
        "cId": 103,
        "primaryCpichPower": 35,
        "primaryScramblingCode": 125,
        "uarfcnDl": 10662,
        "uarfcnUl": 9662,
        "userLabel": "Kairouan South",
        "Lac": 1003,
        "Rac": 23,
        "LAT": 35.6655,
        "LONG": 10.1088,
        "AZIMUTH": 240,
        "P_SiteName": "KAI-SITE-C",
        "administrativeState": "UNLOCKED",
        "operationalState": "ENABLED",
        "Ura": 3,
        "maximumTransmissionPower": 42,
        "NodeId": "NODE-KAI-003",
        "LogicalSite": "Kairouan South",
        "Region": "Kairouan"
    }
]